fraddress/__init__.py
fraddress/learned_settings.crfsuite
fraddress-0.0.4.dist-info/LICENSE
fraddress-0.0.4.dist-info/METADATA
fraddress-0.0.4.dist-info/WHEEL
fraddress-0.0.4.dist-info/top_level.txt
fraddress-0.0.4.dist-info/RECORD
