Metadata-Version: 2.1
Name: fraddress
Version: 0.0.4
Summary: Library for parsing unstructured FR addresses strings into address components
Home-page: https://github.com/fahrtass/fraddress-parser
Author: Mathieu FRANCK
License: The MIT License: http://www.opensource.org/licenses/mit-license.php
Platform: UNKNOWN
Classifier: Development Status :: 3 - Alpha
Classifier: Intended Audience :: Developers
Classifier: Intended Audience :: Science/Research
Classifier: License :: OSI Approved :: MIT License
Classifier: Natural Language :: English
Classifier: Operating System :: MacOS :: MacOS X
Classifier: Operating System :: Microsoft :: Windows
Classifier: Operating System :: POSIX
Classifier: Topic :: Software Development :: Libraries :: Python Modules
Classifier: Topic :: Scientific/Engineering
Classifier: Topic :: Scientific/Engineering :: Information Analysis
Requires-Dist: python-crfsuite (>=0.7)
Requires-Dist: lxml
